utilities_arithmetic/__init__.py
utilities_arithmetic/utilities_arithmetic.py
utilities_arithmetic-2.0.7.dist-info/METADATA
utilities_arithmetic-2.0.7.dist-info/WHEEL
utilities_arithmetic-2.0.7.dist-info/top_level.txt
utilities_arithmetic-2.0.7.dist-info/RECORD
