Metadata-Version: 2.1
Name: utilities-arithmetic
Version: 2.0.7
Summary: A package for performing arithmetic operations
Author: Kathir
Author-email: KathirvelMurugan.SivaSubramanian@cognizant.com
Classifier: Development Status :: 3 - Alpha
Classifier: Intended Audience :: Developers
Classifier: License :: OSI Approved :: MIT License
Classifier: Programming Language :: Python :: 3
Classifier: Programming Language :: Python :: 3.6
Classifier: Programming Language :: Python :: 3.7
Classifier: Programming Language :: Python :: 3.8
Requires-Dist: setuptools
Requires-Dist: twine
Requires-Dist: wheel
